{
  "exports": [
    {
      "id": "0b0a5069-c1a3-4920-bc32-9c947cf24d21",
      "type": "greenscreen",
      "status": "ready",
      "createdAt": "2026-07-04T12:57:02.866Z",
      "updatedAt": "2026-07-04T12:57:07.384Z",
      "title": "oh man cutting those podcast clips later is gonna be a pain",
      "caption": "oh man cutting those podcast clips later is gonna be a pain",
      "sourceConfig": {
        "caption": "oh man cutting those podcast clips later is gonna be a pain",
        "meme": {
          "id": "greenscreen-memes-money-fan-mp4",
          "name": "Money Fan",
          "path": "greenscreen_memes/Money Fan.mp4",
          "url": "/api/local-assets/greenscreen_memes/Money%20Fan.mp4",
          "kind": "video"
        },
        "selectedMeme": 3,
        "background": {
          "id": "stored-ingame-photos-2",
          "title": "Ingame photos",
          "description": "",
          "dominantColor": "#d9d8d0",
          "imageUrl": "/api/local-assets/image-collections/files/ingame-photos-12987-0002-406562-4f8059e56a.png",
          "sourceUrl": "/api/local-assets/image-collections/files/ingame-photos-12987-0002-406562-4f8059e56a.png"
        },
        "backgroundCollectionId": "collection-ingame-photos-2026-07-03t00-00-02-000z",
        "backgroundCollectionTitle": "Ingame photos",
        "selectedBackground": 2,
        "sound": {
          "id": "music-daniel-s-saved-ig-music-21-savage-redrum-instrumental-mp3",
          "name": "21 Savage redrum (INSTRUMENTAL)",
          "path": "music/Daniel's Saved IG Music/21 Savage - redrum (INSTRUMENTAL).mp3",
          "url": "/api/local-assets/music/Daniel's%20Saved%20IG%20Music/21%20Savage%20-%20redrum%20(INSTRUMENTAL).mp3",
          "kind": "audio"
        },
        "textPlacement": "top"
      },
      "previewUrl": "/api/local-assets/assets/files/1783169827300-87e0c0e9-6e8e-4a1a-bd37-c5d8e050c783.jpg",
      "videoUrl": "/api/local-assets/assets/files/1783169827299-89f791f1-c5ab-4b74-b21c-1dea7dc4e647.webm"
    }
  ]
}
